{
  "type": "connection",
  "id": "ba40e1ef-8213-4fb2-a9ce-fc7549c38657",
  "status": "active",
  "createdDate": "2025-08-14T22:37:41Z",
  "lastUsed": "2025-08-14T22:37:42Z",
  "mfaEnabled": false,
  "method": "web",
  "expiryDate": "",
  "profile": {
    "fullName": "Max Wentworth-Smith",
    "firstName": "Max",
    "lastName": "Wentworth-Smith",
    "middleName": "",
    "phoneNumbers": [
      "040534555 ### 991"
    ],
    "emailAddresses": [
      "maxsmith@gmail.com"
    ],
    "physicalAddresses": [
      {
        "addressLine1": "91 Fisher Road",
        "addressLine2": null,
        "addressLine3": null,
        "postcode": "2099",
        "city": "Dee Why",
        "state": "NSW",
        "country": "Australia",
        "countryCode": "AU",
        "formattedAddress": "13/91 Fisher Rd, Dee Why NSW 2099, Australia"
      }
    ]
  },
  "institution": {
    "type": "institution",
    "id": "AU00000",
    "links": {
      "self": "https://au-api.basiq.io/institutions/AU00000"
    }
  },
  "accounts": {
    "type": "list",
    "data": [
      {
        "type": "account",
        "id": "056a34bc-169f-4b03-867f-42cb1f09393a",
        "accountNo": "34567834567890",
        "name": "Savings 123890",
        "currency": "AUD",
        "class": {
          "type": "savings",
          "product": "Hooli Saver"
        },
        "balance": "-4057.00",
        "availableFunds": "-4057.00",
        "lastUpdated": "2025-08-14T14:00:00Z",
        "status": "available",
        "links": {
          "self": "https://au-api.basiq.io/users/5927ff82-45bc-42fa-9c99-f9689a806495/accounts/056a34bc-169f-4b03-867f-42cb1f09393a",
          "transactions": "https://au-api.basiq.io/users/5927ff82-45bc-42fa-9c99-f9689a806495/transactions?filter=account.id.eq('056a34bc-169f-4b03-867f-42cb1f09393a')"
        }
      },
      {
        "type": "account",
        "id": "1c155fc4-f959-4a66-84b9-b0459967fd94",
        "accountNo": "12345612345678",
        "name": "Mortgage 746833",
        "currency": "AUD",
        "class": {
          "type": "mortgage",
          "product": "Hooli Home Loan"
        },
        "balance": "-775525.00",
        "availableFunds": "9033.25",
        "lastUpdated": "2025-08-14T14:00:00Z",
        "status": "available",
        "links": {
          "self": "https://au-api.basiq.io/users/5927ff82-45bc-42fa-9c99-f9689a806495/accounts/1c155fc4-f959-4a66-84b9-b0459967fd94",
          "transactions": "https://au-api.basiq.io/users/5927ff82-45bc-42fa-9c99-f9689a806495/transactions?filter=account.id.eq('1c155fc4-f959-4a66-84b9-b0459967fd94')"
        }
      },
      {
        "type": "account",
        "id": "b5c7f41a-4298-4dcb-baa2-9228e77ac670",
        "accountNo": "23456723456789",
        "name": "Credit Card 13000",
        "currency": "AUD",
        "class": {
          "type": "credit-card",
          "product": "Hooli Visa"
        },
        "balance": "-2194.95",
        "availableFunds": "-2194.95",
        "lastUpdated": "2025-08-14T14:00:00Z",
        "status": "available",
        "links": {
          "self": "https://au-api.basiq.io/users/5927ff82-45bc-42fa-9c99-f9689a806495/accounts/b5c7f41a-4298-4dcb-baa2-9228e77ac670",
          "transactions": "https://au-api.basiq.io/users/5927ff82-45bc-42fa-9c99-f9689a806495/transactions?filter=account.id.eq('b5c7f41a-4298-4dcb-baa2-9228e77ac670')"
        }
      },
      {
        "type": "account",
        "id": "bb0433b5-9f55-42ed-a7cd-baaa1371bf78",
        "accountNo": "45678945678901",
        "name": "Transaction 14000",
        "currency": "AUD",
        "class": {
          "type": "transaction",
          "product": "Hooli Transaction"
        },
        "balance": "14178.82",
        "availableFunds": "14178.82",
        "lastUpdated": "2025-08-14T14:00:00Z",
        "status": "available",
        "links": {
          "self": "https://au-api.basiq.io/users/5927ff82-45bc-42fa-9c99-f9689a806495/accounts/bb0433b5-9f55-42ed-a7cd-baaa1371bf78",
          "transactions": "https://au-api.basiq.io/users/5927ff82-45bc-42fa-9c99-f9689a806495/transactions?filter=account.id.eq('bb0433b5-9f55-42ed-a7cd-baaa1371bf78')"
        }
      }
    ]
  },
  "links": {
    "self": "https://au-api.basiq.io/users/5927ff82-45bc-42fa-9c99-f9689a806495/connections/ba40e1ef-8213-4fb2-a9ce-fc7549c38657",
    "accounts": "https://au-api.basiq.io/users/5927ff82-45bc-42fa-9c99-f9689a806495/accounts?filter=institution.id.eq('AU00000')",
    "transactions": "https://au-api.basiq.io/users/5927ff82-45bc-42fa-9c99-f9689a806495/transactions?filter=institution.id.eq('AU00000')",
    "user": "https://au-api.basiq.io/users/5927ff82-45bc-42fa-9c99-f9689a806495"
  }
}